gispandas/__init__.py
gispandas/mxclf.py
gispandas/mxgdal.py
gispandas/mxgee.py
gispandas/mxgpd.py
gispandas-0.1.9.data/data/README.md
gispandas-0.1.9.dist-info/METADATA
gispandas-0.1.9.dist-info/WHEEL
gispandas-0.1.9.dist-info/top_level.txt
gispandas-0.1.9.dist-info/RECORD
