Metadata-Version: 2.1
Name: gispandas
Version: 0.1.9
Summary: gispandas
Home-page: https://github.com/mxhou/gispandas/
Author: HMX
Author-email: kzdhb8023@163.com
License: MIT
Keywords: gis,geo,tif,json,shp
Requires-Python: >=3.6
